CHANGES.rst
MANIFEST.in
README.rst
TODO.txt
setup.py
docs/INSTALL.txt
docs/LICENSE.GPL
docs/LICENSE.txt
src/plone/__init__.py
src/plone.app.workflowmanager_overhaul.egg-info/PKG-INFO
src/plone.app.workflowmanager_overhaul.egg-info/SOURCES.txt
src/plone.app.workflowmanager_overhaul.egg-info/dependency_links.txt
src/plone.app.workflowmanager_overhaul.egg-info/entry_points.txt
src/plone.app.workflowmanager_overhaul.egg-info/namespace_packages.txt
src/plone.app.workflowmanager_overhaul.egg-info/not-zip-safe
src/plone.app.workflowmanager_overhaul.egg-info/requires.txt
src/plone.app.workflowmanager_overhaul.egg-info/top_level.txt
src/plone/app/__init__.py
src/plone/app/workflowmanager/__init__.py
src/plone/app/workflowmanager/actionmanager.py
src/plone/app/workflowmanager/browser.txt
src/plone/app/workflowmanager/configure.zcml
src/plone/app/workflowmanager/graphviz.py
src/plone/app/workflowmanager/permissions.py
src/plone/app/workflowmanager/testing.py
src/plone/app/workflowmanager/utils.py
src/plone/app/workflowmanager/browser/__init__.py
src/plone/app/workflowmanager/browser/actions.py
src/plone/app/workflowmanager/browser/configure.zcml
src/plone/app/workflowmanager/browser/controlpanel.py
src/plone/app/workflowmanager/browser/layout.py
src/plone/app/workflowmanager/browser/state.py
src/plone/app/workflowmanager/browser/transition.py
src/plone/app/workflowmanager/browser/validators.py
src/plone/app/workflowmanager/browser/workflow.py
src/plone/app/workflowmanager/browser/resources/bootstrap-orig.css
src/plone/app/workflowmanager/browser/resources/bootstrap-popover.js
src/plone/app/workflowmanager/browser/resources/bootstrap.css
src/plone/app/workflowmanager/browser/resources/drag-on.js
src/plone/app/workflowmanager/browser/resources/fix-bootstrap.py
src/plone/app/workflowmanager/browser/resources/springy.js
src/plone/app/workflowmanager/browser/resources/springyui.js
src/plone/app/workflowmanager/browser/resources/workflow-graph.css
src/plone/app/workflowmanager/browser/resources/workflow-graph.js
src/plone/app/workflowmanager/browser/resources/workflowmanager.css
src/plone/app/workflowmanager/browser/resources/workflowmanager.js
src/plone/app/workflowmanager/browser/resources/jsPlumb/Gruntfile.js
src/plone/app/workflowmanager/browser/resources/jsPlumb/build-support.js
src/plone/app/workflowmanager/browser/resources/jsPlumb/changelog.txt
src/plone/app/workflowmanager/browser/resources/jsPlumb/jsPlumb-GPLv2-LICENSE.txt
