Metadata-Version: 1.1
Name: plone.app.workflowmanager-overhaul
Version: 1.2a1
Summary: A workflow manager for Plone
Home-page: https://github.com/plone/plone.app.workflowmanager
Author: Nathan Van Gheem
Author-email: plone-developers@lists.sourceforge.net
License: GPL
Keywords: plone workflow manager gui
Platform: UNKNOWN
Classifier: Framework :: Plone
Classifier: Framework :: Plone :: 4.3
Classifier: Intended Audience :: Customer Service
Classifier: Intended Audience :: Developers
Classifier: License :: OSI Approved :: GNU General Public License (GPL)
Classifier: Operating System :: OS Independent
Classifier: Programming Language :: Other Scripting Engines
Classifier: Programming Language :: Python
Classifier: Topic :: Internet :: WWW/HTTP :: Site Management
Classifier: Topic :: Software Development :: Libraries :: Python Modules
